exp4/stack/stack.v
`timescale 1ns / 1ps

module stack(
    input clk,
    input rstN,
    input [3:0] data_in,
    input push,
    input pop,
    output [3:0] data_out,
    output full,
    output empty
    );
    // point to the empty index of stack
    reg [3:0]emptyPos = 0;
    // stack with depth 8 and width 4
    reg [3:0]stack[0:7];
    // out register
    reg [3:0] out = 0;
    
    // assign empty and full signals
    assign full = (emptyPos == 8);
    assign empty = (emptyPos == 0);
    assign data_out = out;
    
    always @ (posedge clk or negedge rstN) begin
       if (!rstN) begin
            emptyPos <= 0;
            out <= 0;
       end else if (pop && push) begin
            if (empty) begin // If Pop and Push together but pop can't be done
                stack[emptyPos] = data_in;
                emptyPos = emptyPos + 1;
            end else begin // push and pop together
                out = stack[emptyPos - 1];
                stack[emptyPos - 1] = data_in;
            end
        end else if (pop && ~empty) begin // if only pop and pop is valid
            emptyPos = emptyPos - 1;
            out = stack[emptyPos];
        end else if (push && ~full) begin // if only push and push is valid
            stack[emptyPos] = data_in;
            emptyPos = emptyPos + 1;      
        end
    end
endmodule

exp4/stack/stack_tb.v
`timescale 1ns / 1ps
// Stack Test Bench

module stack_tb();
    reg clk = 0, pop = 0, push = 0, rstN = 1;
    reg [3:0]data_in = 0;
    wire [3:0] data_out;
    wire full, empty;
    stack uut(
        .clk (clk),.rstN (rstN),.data_in (data_in),.push (push),.pop (pop),
        .data_out (data_out),.full (full),.empty (empty)
    );
    
    // Generating Clock Signal
    initial begin 
        forever
            #5 clk = ~clk;
    end
    integer i = 0;
    initial begin 
        $dumpfile("stack_test.vcd");
        $dumpvars(0,stack_tb);
        #10;
        // push 5 data every clock
        push = 1;
        for (i = 0; i<5; i = i + 1) begin data_in = $random; #10; end
        // pop last data
        push = 0;
        pop = 1; #10;
        // push pop in one clock
        data_in = 4;
        push = 1; #10;
        // pop again result must be 4
        push = 0; #10;
        // push 6 data (5 valid push / one invelid push)
        pop = 0; push =1;
        for (i = 0; i<6; i = i + 1) begin data_in = $random; #10; end
        // pop last 3 data (it should be the 5th data in last push part)
        push = 0; 
        pop =1; #30;
        // reset the stack
        pop =0; rstN = 0; #5 rstN = 1; #5;
        // 2 invalid pop
        pop = 1; #20;
        // push a new data with pop on and pop it
        data_in = 14; push = 1; #10; // push data with push and pop on but pop is invalid
        push = 0; #10; //pop the last entry
        // change in data with push off
        pop = 0;
        for (i = 0; i<3; i = i + 1) begin data_in = $random; #10; end // change data in with push off
        #5 $finish;
    end
endmodule

exp4/stack/stack_test.vcd
$date
	Tue Apr 13 18:16:36 2021
$end
$version
	Icarus Verilog
$end
$timescale
	1ps
$end
$scope module stack_tb $end
$var wire 1 ! full $end
$var wire 1 " empty $end
$var wire 4 # data_out [3:0] $end
$var reg 1 $ clk $end
$var reg 4 % data_in [3:0] $end
$var reg 1 & pop $end
$var reg 1 ' push $end
$var reg 1 ( rstN $end
$var integer 32 ) i [31:0] $end
$scope module uut $end
$var wire 1 $ clk $end
$var wire 4 * data_in [3:0] $end
$var wire 4 + data_out [3:0] $end
$var wire 1 & pop $end
$var wire 1 ' push $end
$var wire 1 ( rstN $end
$var wire 1 ! full $end
$var wire 1 " empty $end
$var reg 4 , emptyPos [3:0] $end
$var reg 4 - out [3:0] $end
$upscope $end
$upscope $end
$enddefinitions $end
#0
$dumpvars
b0 -
b0 ,
b0 +
b0 *
b0 )
1(
0'
0&
b0 %
0$
b0 #
1"
0!
$end
#5000
1$
#10000
0$
b100 %
b100 *
1'
#15000
0"
b1 ,
1$
#20000
0$
b1 %
b1 *
b1 )
#25000
b10 ,
1$
#30000
0$
b1001 %
b1001 *
b10 )
#35000
b11 ,
1$
#40000
0$
b11 %
b11 *
b11 )
#45000
b100 ,
1$
#50000
0$
b1101 %
b1101 *
b100 )
#55000
b101 ,
1$
#60000
0$
1&
0'
b101 )
#65000
b1101 #
b1101 +
b1101 -
b100 ,
1$
#70000
0$
1'
b100 %
b100 *
#75000
b11 #
b11 +
b11 -
1$
#80000
0$
0'
#85000
b100 #
b100 +
b100 -
b11 ,
1$
#90000
0$
b1101 %
b1101 *
b0 )
1'
0&
#95000
b100 ,
1$
#100000
0$
b101 %
b101 *
b1 )
#105000
b101 ,
1$
#110000
0$
b10 %
b10 *
b10 )
#115000
b110 ,
1$
#120000
0$
b1 %
b1 *
b11 )
#125000
b111 ,
1$
#130000
0$
b1101 %
b1101 *
b100 )
#135000
1!
b1000 ,
1$
#140000
0$
b110 %
b110 *
b101 )
#145000
1$
#150000
0$
1&
0'
b110 )
#155000
b1101 #
b1101 +
b1101 -
0!
b111 ,
1$
#160000
0$
#165000
b1 #
b1 +
b1 -
b110 ,
1$
#170000
0$
#175000
b10 #
b10 +
b10 -
b101 ,
1$
#180000
b0 #
b0 +
b0 -
1"
b0 ,
0$
0(
0&
#185000
1$
1(
#190000
0$
1&
#195000
1$
#200000
0$
#205000
1$
#210000
0$
1'
b1110 %
b1110 *
#215000
0"
b1 ,
1$
#220000
0$
0'
#225000
b1110 #
b1110 +
b1110 -
1"
b0 ,
1$
#230000
0$
b1101 %
b1101 *
b0 )
0&
#235000
1$
#240000
0$
b1 )
#245000
1$
#250000
0$
b1100 %
b1100 *
b10 )
#255000
1$
#260000
0$
b11 )
