exp3/1-combinational comparator/one_bit_comparator.v
module one_bit_comparator (
    A,
    B,
    G_in,
    E_in,
    L_in,
    G_o,
    E_o,
    L_o
);

input wire A, B, G_in, E_in, L_in;
output wire G_o, E_o, L_o;
assign G_o = (A > B) || ((A == B) && G_in);
assign E_o = (A == B) && E_in;
assign L_o = (A < B) || ((A == B) && L_in);

endmodule

exp3/1-combinational comparator/one_bit_comparator_tb.v
module one_bit_comparator_tb;
    reg G_in, E_in, L_in, A, B;
    wire G_o, E_o, L_o;
    one_bit_comparator comparator(
        .A(A),
        .B(B),
        .G_in(G_in),
        .E_in(E_in),
        .L_in(L_in),
        .G_o(G_o),
        .E_o(E_o),
        .L_o(L_o)
    );

    initial begin
        // $dumpfile("test.vcd");
        // $dumpvars(0,one_bit_comparator_tb);
        G_in <= 0;
        E_in <= 1;
        L_in <= 0;
        A <= 0;
        B <= 0;
        #10;
        A <= 0;
        B <= 1;
        #10;
        A <= 1;
        B <= 0;
        #10;
        A <= 1;
        B <= 1;
        #10;

        G_in <= 1;
        E_in <= 0;
        L_in <= 0;
        A <= 0;
        B <= 0;
        #10;
        A <= 0;
        B <= 1;
        #10;
        A <= 1;
        B <= 0;
        #10;
        A <= 1;
        B <= 1;
        #10;

        G_in <= 0;
        E_in <= 0;
        L_in <= 1;
        A <= 0;
        B <= 0;
        #10;
        A <= 0;
        B <= 1;
        #10;
        A <= 1;
        B <= 0;
        #10;
        A <= 1;
        B <= 1;
        #10;
    end
endmodule

exp3/1-combinational comparator/vcd/1_comparator_test.vcd
$date
	Tue Apr  6 01:56:23 2021
$end
$version
	Icarus Verilog
$end
$timescale
	1s
$end
$scope module one_bit_comparator_tb $end
$var wire 1 ! L_o $end
$var wire 1 " G_o $end
$var wire 1 # E_o $end
$var reg 1 $ A $end
$var reg 1 % B $end
$var reg 1 & E_in $end
$var reg 1 ' G_in $end
$var reg 1 ( L_in $end
$scope module comparator $end
$var wire 1 $ A $end
$var wire 1 % B $end
$var wire 1 & E_in $end
$var wire 1 # E_o $end
$var wire 1 ' G_in $end
$var wire 1 " G_o $end
$var wire 1 ( L_in $end
$var wire 1 ! L_o $end
$upscope $end
$upscope $end
$enddefinitions $end
#0
$dumpvars
0(
0'
1&
0%
0$
1#
0"
0!
$end
#10
0#
1!
1%
#20
1"
0!
0%
1$
#30
1#
0"
1%
#40
1"
0#
0%
0$
0&
1'
#50
0"
1!
1%
#60
1"
0!
0%
1$
#70
1"
1%
#80
0"
1!
0%
0$
1(
0'
#90
1%
#100
1"
0!
0%
1$
#110
1!
0"
1%
