exp10/processor/processor.v
module processor (
    output signed [7:0] direct_read_data,
    input [7:0] direct_read_address,
    input [7:0] direct_write_address,
    input signed [7:0] direct_write_data,
    input direct_memory_write,
    input clk,
    input resetN,
    input haltN
);
    localparam PUSHC = 4'b0000;
    localparam PUSH = 4'b0001;
    localparam POP = 4'b0010;
    localparam JUMP = 4'b0011;
    localparam JZ = 4'b0100;
    localparam JS = 4'b0101;
    localparam ADD = 4'b0110;
    localparam SUB = 4'b0111;

    reg [7:0] pc, next_pc;
    reg z_flag, s_flag, push, pop, mem_write;

    // stack
    reg [3:0] stack_pointer; // empty position at the top of stack
    reg signed [7:0] stack_mem [0:7];
    reg signed [7:0] data_to_memory, data_to_stack;
    wire stack_full = (stack_pointer == 8);
    wire stack_empty = (stack_pointer == 0);
    wire [7:0] top_of_stack = stack_empty ? 0 : stack_mem[stack_pointer - 1];

    // instruction memory
    // reg [11:0] instruction_memory [0:255];
    // wire [11:0] instruction = instruction_memory[pc];
    wire [11:0] instruction = {data_memory[pc][7:4], data_memory[pc + 1][7:0]};
    wire [3:0] opcode = instruction[11:8];
    wire [7:0] operand = instruction[7:0];

    // data memory
    reg signed [7:0] data_memory [0:255];
    wire [7:0] memory_read_address = operand;
    wire [7:0] memory_write_address = operand;
    wire [7:0] data_from_memory = data_memory[memory_read_address];
    assign direct_read_data = data_memory[direct_read_address];

    always @(*) begin
        next_pc = pc + 1;
        push = 0;
        pop = 0;
        mem_write = 0;
        case (opcode)
            PUSHC: begin
                next_pc = pc + 2;
                push = 1;
                data_to_stack = operand;
            end
            PUSH: begin
                next_pc = pc + 2;
                push = 1;
                data_to_stack = data_from_memory;
            end
            POP: begin
                next_pc = pc + 2;
                pop = 1;
                mem_write = 1;
                data_to_memory = top_of_stack;
            end
            JUMP: begin
                pop = 1;
                next_pc = top_of_stack;
            end
            JZ: begin
                if (z_flag) begin
                    pop = 1;
                    next_pc = top_of_stack;
                end
            end
            JS: begin
                if (s_flag) begin
                    pop = 1;
                    next_pc = top_of_stack;
                end
            end
        endcase
    end

    integer i;
    always @(posedge clk or negedge resetN) begin
        if (~resetN) begin
            pc <= 0;
            z_flag <= 0;
            s_flag <= 0;
            stack_pointer <= 0;
            for (i = 0; i < 256; i = i + 1) begin
                data_memory[i] <= 8'b0;
            end
        end
        else if (haltN) begin
            pc <= next_pc;
            case (opcode)
                ADD: begin
                    stack_mem[stack_pointer - 2] <= stack_mem[stack_pointer - 1] + stack_mem[stack_pointer - 2];
                    stack_pointer <= stack_pointer - 1;
                    z_flag <= (stack_mem[stack_pointer - 1] + stack_mem[stack_pointer - 2] == 0);
                    s_flag <= (stack_mem[stack_pointer - 1] + stack_mem[stack_pointer - 2] < 0);
                end
                SUB: begin
                    stack_mem[stack_pointer - 2] <= stack_mem[stack_pointer - 2] - stack_mem[stack_pointer - 1];
                    stack_pointer <= stack_pointer - 1;
                    z_flag <= (stack_mem[stack_pointer - 2] - stack_mem[stack_pointer - 1] == 0);
                    s_flag <= (stack_mem[stack_pointer - 2] - stack_mem[stack_pointer - 1] < 0);
                end
                default: begin
                    if (pop & ~stack_empty) begin
                        stack_pointer <= stack_pointer - 1;
                    end
                    if (push & ~stack_full) begin
                        stack_mem[stack_pointer] <= data_to_stack;
                        stack_pointer <= stack_pointer + 1;
                    end
                    if (mem_write) begin
                        data_memory[memory_write_address] <= data_to_memory;
                    end
                end
            endcase
        end
        else begin
            if (direct_memory_write) begin
                data_memory[direct_write_address] <= direct_write_data;
            end
        end
    end
endmodule

exp10/processor/processor_tb.v
module processor_tb ();
    wire [7:0] direct_read_data;
    reg [7:0] direct_read_address;
    reg [7:0] direct_write_address;
    reg [7:0] direct_write_data;
    reg direct_memory_write;
    reg clk;
    reg resetN;
    reg haltN;

    processor p(
        .direct_read_data(direct_read_data), 
        .direct_read_address(direct_read_address),
        .direct_write_address(direct_write_address),
        .direct_write_data(direct_write_data),
        .direct_memory_write(direct_memory_write),
        .clk(clk),
        .resetN(resetN),
        .haltN(haltN)
    );

    initial begin
        clk = 0;
        forever #5 clk = ~clk;
    end

    reg [11:0] instructions [0:127];
    integer i;
    initial begin
        $dumpfile("processor.vcd");
        $dumpvars(0, processor_tb);
        $dumpvars(0, p);

        instructions[0] = 12'b000111111111;
        instructions[1] = 12'b000000010111;
        instructions[2] = 12'b011000000000;
        instructions[3] = 12'b001011111111;
        instructions[4] = 12'b000111111111;
        instructions[5] = 12'b000111111111;
        instructions[6] = 12'b011000000000;
        instructions[7] = 12'b000000001100;
        instructions[8] = 12'b011100000000;
        instructions[9] = 12'b001011111111;

        haltN = 0;
        resetN = 0;
        direct_read_address = 255;
        direct_memory_write = 0;
        #10 resetN = 1;
        direct_memory_write = 1;
        direct_write_address = 0;
        for (i = 0; i < 10; i = i + 1) begin
            direct_write_data = {instructions[i][11:8], 4'b0000};
            #10;
            direct_write_address = direct_write_address + 1;
            if (instructions[i][11:8] < 3) begin
                direct_write_data = instructions[i][7:0];
                #10;
                direct_write_address = direct_write_address + 1;
            end
        end
        direct_write_address = 255;
        direct_write_data = 17;
        #10;
        direct_memory_write = 0;
        haltN = 1;
        #100;
        haltN = 0;
        #10;
        $finish;
    end
endmodule

exp10/processor/processor.vcd
$date
	Wed Jun  2 08:16:44 2021
$end
$version
	Icarus Verilog
$end
$timescale
	1s
$end
$scope module processor_tb $end
$var wire 8 ! direct_read_data [7:0] $end
$var reg 1 " clk $end
$var reg 1 # direct_memory_write $end
$var reg 8 $ direct_read_address [7:0] $end
$var reg 8 % direct_write_address [7:0] $end
$var reg 8 & direct_write_data [7:0] $end
$var reg 1 ' haltN $end
$var reg 1 ( resetN $end
$var integer 32 ) i [31:0] $end
$scope module p $end
$var wire 1 " clk $end
$var wire 8 * data_from_memory [7:0] $end
$var wire 1 # direct_memory_write $end
$var wire 8 + direct_read_address [7:0] $end
$var wire 8 , direct_read_data [7:0] $end
$var wire 8 - direct_write_address [7:0] $end
$var wire 8 . direct_write_data [7:0] $end
$var wire 1 ' haltN $end
$var wire 8 / memory_read_address [7:0] $end
$var wire 8 0 memory_write_address [7:0] $end
$var wire 1 ( resetN $end
$var wire 8 1 top_of_stack [7:0] $end
$var wire 1 2 stack_full $end
$var wire 1 3 stack_empty $end
$var wire 8 4 operand [7:0] $end
$var wire 4 5 opcode [3:0] $end
$var wire 12 6 instruction [11:0] $end
$var reg 8 7 data_to_memory [7:0] $end
$var reg 8 8 data_to_stack [7:0] $end
$var reg 1 9 mem_write $end
$var reg 8 : next_pc [7:0] $end
$var reg 8 ; pc [7:0] $end
$var reg 1 < pop $end
$var reg 1 = push $end
$var reg 1 > s_flag $end
$var reg 4 ? stack_pointer [3:0] $end
$var reg 1 @ z_flag $end
$var integer 32 A i [31:0] $end
$upscope $end
$upscope $end
$scope module processor_tb $end
$scope module p $end
$upscope $end
$upscope $end
$enddefinitions $end
#0
$dumpvars
b100000000 A
0@
b0 ?
0>
1=
0<
b0 ;
b10 :
09
b0 8
bx 7
b0 6
b0 5
b0 4
13
02
b0 1
b0 0
b0 /
bx .
bx -
b0 ,
b11111111 +
b0 *
bx )
0(
0'
bx &
bx %
b11111111 $
0#
0"
b0 !
$end
#5
b100000000 A
1"
#10
0"
b10000 &
b10000 .
b0 )
b0 %
b0 -
1#
1(
#15
b10000 8
b1 5
b100000000 6
1=
b10 :
b10000 *
1"
#20
0"
b11111111 &
b11111111 .
b1 %
b1 -
#25
b0 8
1=
b10 :
b11111111 0
b0 *
b11111111 /
b11111111 4
b111111111 6
1"
#30
0"
b0 &
b0 .
b1 )
b10 %
b10 -
#35
1"
#40
0"
b10111 &
b10111 .
b11 %
b11 -
#45
1"
#50
0"
b1100000 &
b1100000 .
b10 )
b100 %
b100 -
#55
1"
#60
0"
b100000 &
b100000 .
b11 )
b101 %
b101 -
#65
1"
#70
0"
b11111111 &
b11111111 .
b110 %
b110 -
#75
1"
#80
0"
b10000 &
b10000 .
b100 )
b111 %
b111 -
#85
1"
#90
0"
b11111111 &
b11111111 .
b1000 %
b1000 -
#95
1"
#100
0"
b10000 &
b10000 .
b101 )
b1001 %
b1001 -
#105
1"
#110
0"
b11111111 &
b11111111 .
b1010 %
b1010 -
#115
1"
#120
0"
b1100000 &
b1100000 .
b110 )
b1011 %
b1011 -
#125
1"
#130
0"
b0 &
b0 .
b111 )
b1100 %
b1100 -
#135
1"
#140
0"
b1100 &
b1100 .
b1101 %
b1101 -
#145
1"
#150
0"
b1110000 &
b1110000 .
b1000 )
b1110 %
b1110 -
#155
1"
#160
0"
b100000 &
b100000 .
b1001 )
b1111 %
b1111 -
#165
1"
#170
0"
b11111111 &
b11111111 .
b10000 %
b10000 -
#175
1"
#180
0"
b10001 &
b10001 .
b1010 )
b11111111 %
b11111111 -
#185
b10001 8
1=
b10 :
b10001 *
b10001 !
b10001 ,
1"
#190
0"
1'
0#
#195
b0 5
b10001 1
b10111 8
1=
b100 :
b10111 0
b0 *
b10111 /
b10111 4
03
b1 ?
b10111 6
b10 ;
1"
#200
0"
#205
b110 5
b10111 1
b100000 8
0=
b101 :
b100000 0
b100000 /
b100000 4
b10 ?
b11000100000 6
b100 ;
1"
#210
0"
#215
b101000 7
19
1<
b10 5
b101000 1
b111 :
b11111111 0
b10001 *
b11111111 /
b11111111 4
b1 ?
b1011111111 6
b101 ;
1"
#220
0"
#225
b101000 8
1=
b1 5
b0 1
09
0<
b1001 :
b111111111 6
b101000 *
b101000 !
b101000 ,
13
b0 ?
b111 ;
1"
#230
0"
#235
b101000 1
1=
b1011 :
03
b1 ?
b1001 ;
1"
#240
0"
#245
b110 5
b10000 8
0=
b1100 :
b0 0
b10000 *
b0 /
b0 4
b10 ?
b11000000000 6
b1011 ;
1"
#250
0"
#255
b1100 8
1=
b0 5
b1010000 1
b1110 :
b1100 0
b0 *
b1100 /
b1100 4
b1 ?
b1100 6
b1100 ;
1"
#260
0"
#265
b111 5
b1100 1
b100000 8
0=
b1111 :
b100000 0
b100000 /
b100000 4
b10 ?
b11100100000 6
b1110 ;
1"
#270
0"
#275
b1000100 7
19
1<
b10 5
b1000100 1
b10001 :
b11111111 0
b101000 *
b11111111 /
b11111111 4
b1 ?
b1011111111 6
b1111 ;
1"
#280
0"
#285
b0 8
1=
b0 5
b0 1
09
0<
b10011 :
b0 0
b0 /
b0 4
b10000 *
b1000100 !
b1000100 ,
13
b0 ?
b0 6
b10001 ;
1"
#290
0"
0'
