exp6/Incubator Control/fan_control.v
module fan_control (
    T,
    Cooler,
    CRS,
    OUT,
    clk
);
    input signed [7:0] T;
    input Cooler, clk;
    output reg [3:0] CRS;
    output reg OUT;

    reg S1, S2, S3; // one-hot state indicators

    always @(*) begin
        if (S1) begin
            CRS = 4;
        end
        else if (S2) begin
            CRS = 6;
        end
        else if (S3) begin
            CRS = 8;
        end
        else if (OUT) begin
            CRS = 0;
        end
    end

    always @(posedge clk or negedge Cooler) begin
        if (~Cooler) begin
            S1 <= 0;
            S2 <= 0;
            S3 <= 0;
            OUT <= 1;
        end
        else begin
            if (S1) begin
                if (T < 25) begin
                    S1 <= 0;
                    OUT <= 1;
                end
                if (T > 40) begin
                    S1 <= 0;
                    S2 <= 1;
                end
            end
            else if (S2) begin
                if (T < 35) begin
                    S2 <= 0;
                    S1 <= 1;
                end
                if (T > 45) begin
                    S2 <= 0;
                    S3 <= 1;
                end
            end
            else if (S3) begin
                if (T < 40) begin
                    S3 <= 0;
                    S2 <= 1;
                end
            end
            else if (OUT) begin
                if (T > 35) begin
                    OUT <= 0;
                    S1 <= 1;
                end
            end
        end
    end
endmodule

exp6/Incubator Control/power_control.v
module power_control (
    T,
    Heater,
    Cooler,
    clk,
    rstN
);
    input signed [7:0] T;
    input clk, rstN;
    output Heater, Cooler;

    reg S1, S2, S3; // one-hot state indicators

    assign Heater = S3;
    assign Cooler = S2;

    always @(posedge clk or negedge rstN) begin
        if (~rstN) begin
            S1 <= 1;
            S2 <= 0;
            S3 <= 0;
        end
        else begin
            if (S1) begin
                if (T < 15) begin
                    S1 <= 0;
                    S3 <= 1;
                end
                if (T > 35) begin
                    S1 <= 0;
                    S2 <= 1;
                end
            end
            else if (S2) begin
                if (T < 25) begin
                    S2 <= 0;
                    S1 <= 1;
                end
            end
            else if (S3) begin
                if (T > 30) begin
                    S3 <= 0;
                    S1 <= 1;
                end
            end
        end
    end
endmodule

exp6/Incubator Control/digital_control.v
module digital_control (
    T,
    Heater,
    Cooler,
    CRS,
    OUT,
    clk,
    rstN
);
    input [7:0] T;
    input clk, rstN;
    output Heater, Cooler;
    output [3:0] CRS;

    power_control pcu(.T(T), .Heater(Heater), .Cooler(Cooler), .clk(clk), .rstN(rstN));
    fan_control fcu(.T(T), .Cooler(Cooler), .CRS(CRS), .OUT(OUT), .clk(clk));
endmodule

exp6/Incubator Control/digital_control_rand_tb.v
module digital_control_rand_tb ();
    reg clk, rstN;
    reg [7:0] T;
    wire Heater, Cooler, OUT;
    wire [3:0] CRS;

    digital_control dcu(.Heater(Heater), .Cooler(Cooler), .T(T), .clk(clk), .rstN(rstN), .OUT(OUT), .CRS(CRS));
    
    initial begin
        clk <= 0;
        forever #10 clk <= ~clk;
    end

    reg [6:0] i;
    integer seed;
    initial begin
        $dumpfile("dcu_rand.vcd");
        $dumpvars(0, digital_control_rand_tb);
        seed = $time;
        rstN <= 0;
        #20 rstN <= 1;
        for (i = 0; ~i[6]; i = i + 1) begin
            T = $random(seed) % 71 - 11;
            // rstN = $random(seed);
            #100;
        end
        $finish;
    end
endmodule

exp6/Incubator Control/dcu_rand.vcd
$date
	Mon Apr 26 11:32:15 2021
$end
$version
	Icarus Verilog
$end
$timescale
	1s
$end
$scope module digital_control_rand_tb $end
$var wire 1 ! OUT $end
$var wire 1 " Heater $end
$var wire 1 # Cooler $end
$var wire 4 $ CRS [3:0] $end
$var reg 8 % T [7:0] $end
$var reg 1 & clk $end
$var reg 7 ' i [6:0] $end
$var reg 1 ( rstN $end
$var integer 32 ) seed [31:0] $end
$scope module dcu $end
$var wire 8 * T [7:0] $end
$var wire 1 & clk $end
$var wire 1 ( rstN $end
$var wire 1 ! OUT $end
$var wire 1 " Heater $end
$var wire 1 # Cooler $end
$var wire 4 + CRS [3:0] $end
$scope module fcu $end
$var wire 8 , T [7:0] $end
$var wire 1 & clk $end
$var wire 1 # Cooler $end
$var reg 4 - CRS [3:0] $end
$var reg 1 ! OUT $end
$var reg 1 . S1 $end
$var reg 1 / S2 $end
$var reg 1 0 S3 $end
$upscope $end
$scope module pcu $end
$var wire 1 # Cooler $end
$var wire 1 " Heater $end
$var wire 8 1 T [7:0] $end
$var wire 1 & clk $end
$var wire 1 ( rstN $end
$var reg 1 2 S1 $end
$var reg 1 3 S2 $end
$var reg 1 4 S3 $end
$upscope $end
$upscope $end
$upscope $end
$enddefinitions $end
#0
$dumpvars
04
03
12
bx 1
00
0/
0.
b0 -
bx ,
b0 +
bx *
b0 )
0(
bx '
0&
bx %
b0 $
0#
0"
1!
$end
#10
1&
#20
0&
1(
b11 %
b11 *
b11 ,
b11 1
b10010010000101010011001000000110 )
b0 '
#30
1"
14
02
1&
#40
0&
#50
1&
#60
0&
#70
1&
#80
0&
#90
1&
#100
0&
#110
1&
#120
0&
b11000000 %
b11000000 *
b11000000 ,
b11000000 1
b1000000100010010101110011001111 )
b1 '
#130
1&
#140
0&
#150
1&
#160
0&
#170
1&
#180
0&
#190
1&
#200
0&
#210
1&
#220
0&
b10101111 %
b10101111 *
b10101111 ,
b10101111 1
b100100001001101010011000100 )
b10 '
#230
1&
#240
0&
#250
1&
#260
0&
#270
1&
#280
0&
#290
1&
#300
0&
#310
1&
#320
0&
b10110100 %
b10110100 *
b10110100 ,
b10110100 1
b110001111100000101010011110101 )
b11 '
#330
1&
#340
0&
#350
1&
#360
0&
#370
1&
#380
0&
#390
1&
#400
0&
#410
1&
#420
0&
b10001 %
b10001 *
b10001 ,
b10001 1
b10000110101110010111100100110010 )
b100 '
#430
1&
#440
0&
#450
1&
#460
0&
#470
1&
#480
0&
#490
1&
#500
0&
#510
1&
#520
0&
b111 %
b111 *
b111 ,
b111 1
b11000110110111111001011100001011 )
b101 '
#530
1&
#540
0&
#550
1&
#560
0&
#570
1&
#580
0&
#590
1&
#600
0&
#610
1&
#620
0&
b11101010 %
b11101010 *
b11101010 ,
b11101010 1
b110010110000101000001011010000 )
b110 '
#630
1&
#640
0&
#650
1&
#660
0&
#670
1&
#680
0&
#690
1&
#700
0&
#710
1&
#720
0&
b10110000 %
b10110000 *
b10110000 ,
b10110000 1
b1001001101110101000010010001 )
b111 '
#730
1&
#740
0&
#750
1&
#760
0&
#770
1&
#780
0&
#790
1&
#800
0&
#810
1&
#820
0&
b101011 %
b101011 *
b101011 ,
b101011 1
b10000000111100111110000100011110 )
b1000 '
#830
12
0"
04
1&
#840
0&
#850
1#
13
02
1&
#860
0&
#870
b100 $
b100 +
b100 -
1.
0!
1&
#880
0&
#890
b110 $
b110 +
b110 -
1/
0.
1&
#900
0&
#910
1&
#920
0&
b1100 %
b1100 *
b1100 ,
b1100 1
b10000110110101111100101100000111 )
b1001 '
#930
1!
b0 $
b0 +
b0 -
0.
0/
12
0#
03
1&
#940
0&
#950
1"
14
02
1&
#960
0&
#970
1&
#980
0&
#990
1&
#1000
0&
#1010
1&
#1020
0&
b1010 %
b1010 *
b1010 ,
b1010 1
b10111011001000111110111110011100 )
b1010 '
#1030
1&
#1040
0&
#1050
1&
#1060
0&
#1070
1&
#1080
0&
#1090
1&
#1100
0&
#1110
1&
#1120
0&
b10111 %
b10111 *
b10111 ,
b10111 1
b10011110100011011100101111101101 )
b1011 '
#1130
1&
#1140
0&
#1150
1&
#1160
0&
#1170
1&
#1180
0&
#1190
1&
#1200
0&
#1210
1&
#1220
0&
b10000 %
b10000 *
b10000 ,
b10000 1
b11110110110101000101010111001010 )
b1100 '
#1230
1&
#1240
0&
#1250
1&
#1260
0&
#1270
1&
#1280
0&
#1290
1&
#1300
0&
#1310
1&
#1320
0&
b100011 %
b100011 *
b100011 ,
b100011 1
b11000110001011011111010011000011 )
b1101 '
#1330
12
0"
04
1&
#1340
0&
#1350
1&
#1360
0&
#1370
1&
#1380
0&
#1390
1&
#1400
0&
#1410
1&
#1420
0&
b100000 %
b100000 *
b100000 ,
b100000 1
b11111100111111011110011100101000 )
b1110 '
#1430
1&
#1440
0&
#1450
1&
#1460
0&
#1470
1&
#1480
0&
#1490
1&
#1500
0&
#1510
1&
#1520
0&
b10111110 %
b10111110 *
b10111110 ,
b10111110 1
b1100011001101110010001100001001 )
b1111 '
#1530
1"
14
02
1&
#1540
0&
#1550
1&
#1560
0&
#1570
1&
#1580
0&
#1590
1&
#1600
0&
#1610
1&
#1620
0&
b11011100 %
b11011100 *
b11011100 ,
b11011100 1
b1100010111101111000001100110110 )
b10000 '
#1630
1&
#1640
0&
#1650
1&
#1660
0&
#1670
1&
#1680
0&
#1690
1&
#1700
0&
#1710
1&
#1720
0&
b11000000 %
b11000000 *
b11000000 ,
b11000000 1
b1010101000100111101000000111111 )
b10001 '
#1730
1&
#1740
0&
#1750
1&
#1760
0&
#1770
1&
#1780
0&
#1790
1&
#1800
0&
#1810
1&
#1820
0&
b1101 %
b1101 *
b1101 ,
b1101 1
b11110010101011111111010101110100 )
b10010 '
#1830
1&
#1840
0&
#1850
1&
#1860
0&
#1870
1&
#1880
0&
#1890
1&
#1900
0&
#1910
1&
#1920
0&
b10111110 %
b10111110 *
b10111110 ,
b10111110 1
b111011110100100111000111100101 )
b10011 '
#1930
1&
#1940
0&
#1950
1&
#1960
0&
#1970
1&
#1980
0&
#1990
1&
#2000
0&
#2010
1&
#2020
0&
b11100100 %
b11100100 *
b11100100 ,
b11100100 1
b1001001100101101010101100010 )
b10100 '
#2030
1&
#2040
0&
#2050
1&
#2060
0&
#2070
1&
#2080
0&
#2090
1&
#2100
0&
#2110
1&
#2120
0&
b100001 %
b100001 *
b100001 ,
b100001 1
b11000111111011001101100101111011 )
b10101 '
#2130
12
0"
04
1&
#2140
0&
#2150
1&
#2160
0&
#2170
1&
#2180
0&
#2190
1&
#2200
0&
#2210
1&
#2220
0&
b110011 %
b110011 *
b110011 ,
b110011 1
b11111001001100000110011010000000 )
b10110 '
#2230
1#
13
02
1&
#2240
0&
#2250
b100 $
b100 +
b100 -
1.
0!
1&
#2260
0&
#2270
b110 $
b110 +
b110 -
1/
0.
1&
#2280
0&
#2290
b1000 $
b1000 +
b1000 -
10
0/
1&
#2300
0&
#2310
1&
#2320
0&
b11000100 %
b11000100 *
b11000100 ,
b11000100 1
b1100111011101101001010010000001 )
b10111 '
#2330
1!
b0 $
b0 +
b0 -
0/
00
12
0#
03
1&
#2340
0&
#2350
1"
14
02
1&
#2360
0&
#2370
1&
#2380
0&
#2390
1&
#2400
0&
#2410
1&
#2420
0&
b11000111 %
b11000111 *
b11000111 ,
b11000111 1
b1110100000000000111100001001110 )
b11000 '
#2430
1&
#2440
0&
#2450
1&
#2460
0&
#2470
1&
#2480
0&
#2490
1&
#2500
0&
#2510
1&
#2520
0&
b10110001 %
b10110001 *
b10110001 ,
b10110001 1
b1100010110010100100110001110111 )
b11001 '
#2530
1&
#2540
0&
#2550
1&
#2560
0&
#2570
1&
#2580
0&
#2590
1&
#2600
0&
#2610
1&
#2620
0&
b101110 %
b101110 *
b101110 ,
b101110 1
b10101110010110000100011001001100 )
b11010 '
#2630
12
0"
04
1&
#2640
0&
#2650
1#
13
02
1&
#2660
0&
#2670
b100 $
b100 +
b100 -
1.
0!
1&
#2680
0&
#2690
b110 $
b110 +
b110 -
1/
0.
1&
#2700
0&
#2710
b1000 $
b1000 +
b1000 -
10
0/
1&
#2720
0&
b10110110 %
b10110110 *
b10110110 ,
b10110110 1
b1011110100011100010011011011101 )
b11011 '
#2730
1!
b0 $
b0 +
b0 -
0/
00
12
0#
03
1&
#2740
0&
#2750
1"
14
02
1&
#2760
0&
#2770
1&
#2780
0&
#2790
1&
#2800
0&
#2810
1&
#2820
0&
b11010110 %
b11010110 *
b11010110 ,
b11010110 1
b10110101010110101011111111010 )
b11100 '
#2830
1&
#2840
0&
#2850
1&
#2860
0&
#2870
1&
#2880
0&
#2890
1&
#2900
0&
#2910
1&
#2920
0&
b11100101 %
b11100101 *
b11100101 ,
b11100101 1
b110010101001110010010100110011 )
b11101 '
#2930
1&
#2940
0&
#2950
1&
#2960
0&
#2970
1&
#2980
0&
#2990
1&
#3000
0&
#3010
1&
#3020
0&
b11000100 %
b11000100 *
b11000100 ,
b11000100 1
b110001111011110110000011011000 )
b11110 '
#3030
1&
#3040
0&
#3050
1&
#3060
0&
#3070
1&
#3080
0&
#3090
1&
#3100
0&
#3110
1&
#3120
0&
b110001 %
b110001 *
b110001 ,
b110001 1
b10000101011100111000010011111001 )
b11111 '
#3130
12
0"
04
1&
#3140
0&
#3150
1#
13
02
1&
#3160
0&
#3170
b100 $
b100 +
b100 -
1.
0!
1&
#3180
0&
#3190
b110 $
b110 +
b110 -
1/
0.
1&
#3200
0&
#3210
b1000 $
b1000 +
b1000 -
10
0/
1&
#3220
0&
b11011001 %
b11011001 *
b11011001 ,
b11011001 1
b1000000001110110010000001100110 )
b100000 '
#3230
1!
b0 $
b0 +
b0 -
0/
00
12
0#
03
1&
#3240
0&
#3250
1"
14
02
1&
#3260
0&
#3270
1&
#3280
0&
#3290
1&
#3300
0&
#3310
1&
#3320
0&
b101001 %
b101001 *
b101001 ,
b101001 1
b10010000011001000001111110101111 )
b100001 '
#3330
12
0"
04
1&
#3340
0&
#3350
1#
13
02
1&
#3360
0&
#3370
b100 $
b100 +
b100 -
1.
0!
1&
#3380
0&
#3390
b110 $
b110 +
b110 -
1/
0.
1&
#3400
0&
#3410
1&
#3420
0&
b100110 %
b100110 *
b100110 ,
b100110 1
b11010101011110000100001000100100 )
b100010 '
#3430
1&
#3440
0&
#3450
1&
#3460
0&
#3470
1&
#3480
0&
#3490
1&
#3500
0&
#3510
1&
#3520
0&
b11010100 %
b11010100 *
b11010100 ,
b11010100 1
b1001110110011001100101011010101 )
b100011 '
#3530
1!
b0 $
b0 +
b0 -
0.
0/
12
0#
03
1&
#3540
0&
#3550
1"
14
02
1&
#3560
0&
#3570
1&
#3580
0&
#3590
1&
#3600
0&
#3610
1&
#3620
0&
b11100001 %
b11100001 *
b11100001 ,
b11100001 1
b1001011001000000011110110010010 )
b100100 '
#3630
1&
#3640
0&
#3650
1&
#3660
0&
#3670
1&
#3680
0&
#3690
1&
#3700
0&
#3710
1&
#3720
0&
b10110000 %
b10110000 *
b10110000 ,
b10110000 1
b1001100000111011011111101011 )
b100101 '
#3730
1&
#3740
0&
#3750
1&
#3760
0&
#3770
1&
#3780
0&
#3790
1&
#3800
0&
#3810
1&
#3820
0&
b11001001 %
b11001001 *
b11001001 ,
b11001001 1
b110101111000011011000110000 )
b100110 '
#3830
1&
#3840
0&
#3850
1&
#3860
0&
#3870
1&
#3880
0&
#3890
1&
#3900
0&
#3910
1&
#3920
0&
b11100100 %
b11100100 *
b11100100 ,
b11100100 1
b101001101001111101010001110001 )
b100111 '
#3930
1&
#3940
0&
#3950
1&
#3960
0&
#3970
1&
#3980
0&
#3990
1&
#4000
0&
#4010
1&
#4020
0&
b1111 %
b1111 *
b1111 ,
b1111 1
b10110101100111111101101101111110 )
b101000 '
#4030
1&
#4040
0&
#4050
1&
#4060
0&
#4070
1&
#4080
0&
#4090
1&
#4100
0&
#4110
1&
#4120
0&
b11010000 %
b11010000 *
b11010000 ,
b11010000 1
b1101010101001100010100111100111 )
b101001 '
#4130
1&
#4140
0&
#4150
1&
#4160
0&
#4170
1&
#4180
0&
#4190
1&
#4200
0&
#4210
1&
#4220
0&
b10110011 %
b10110011 *
b10110011 ,
b10110011 1
b1000101110100100011111100 )
b101010 '
#4230
1&
#4240
0&
#4250
1&
#4260
0&
#4270
1&
#4280
0&
#4290
1&
#4300
0&
#4310
1&
#4320
0&
b10111000 %
b10111000 *
b10111000 ,
b10111000 1
b1010111010101100011110111001101 )
b101011 '
#4330
1&
#4340
0&
#4350
1&
#4360
0&
#4370
1&
#4380
0&
#4390
1&
#4400
0&
#4410
1&
#4420
0&
b101001 %
b101001 *
b101001 ,
b101001 1
b10001110111111111110011000101010 )
b101100 '
#4430
12
0"
04
1&
#4440
0&
#4450
1#
13
02
1&
#4460
0&
#4470
b100 $
b100 +
b100 -
1.
0!
1&
#4480
0&
#4490
b110 $
b110 +
b110 -
1/
0.
1&
#4500
0&
#4510
1&
#4520
0&
b11101011 %
b11101011 *
b11101011 ,
b11101011 1
b1100111110001010111000110100011 )
b101101 '
#4530
1!
b0 $
b0 +
b0 -
0.
0/
12
0#
03
1&
#4540
0&
#4550
1"
14
02
1&
#4560
0&
#4570
1&
#4580
0&
#4590
1&
#4600
0&
#4610
1&
#4620
0&
b1 %
b1 *
b1 ,
b1 1
b10010001100001000100011010001000 )
b101110 '
#4630
1&
#4640
0&
#4650
1&
#4660
0&
#4670
1&
#4680
0&
#4690
1&
#4700
0&
#4710
1&
#4720
0&
b101100 %
b101100 *
b101100 ,
b101100 1
b10000101000010010110001011101001 )
b101111 '
#4730
12
0"
04
1&
#4740
0&
#4750
1#
13
02
1&
#4760
0&
#4770
b100 $
b100 +
b100 -
1.
0!
1&
#4780
0&
#4790
b110 $
b110 +
b110 -
1/
0.
1&
#4800
0&
#4810
1&
#4820
0&
b11100000 %
b11100000 *
b11100000 ,
b11100000 1
b1100101011100110000100110010110 )
b110000 '
#4830
1!
b0 $
b0 +
b0 -
0.
0/
12
0#
03
1&
#4840
0&
#4850
1"
14
02
1&
#4860
0&
#4870
1&
#4880
0&
#4890
1&
#4900
0&
#4910
1&
#4920
0&
b11101101 %
b11101101 *
b11101101 ,
b11101101 1
b11110001100010100101100011111 )
b110001 '
#4930
1&
#4940
0&
#4950
1&
#4960
0&
#4970
1&
#4980
0&
#4990
1&
#5000
0&
#5010
1&
#5020
0&
b11111101 %
b11111101 *
b11111101 ,
b11111101 1
b11111001011010001011101011010100 )
b110010 '
#5030
1&
#5040
0&
#5050
1&
#5060
0&
#5070
1&
#5080
0&
#5090
1&
#5100
0&
#5110
1&
#5120
0&
b11110101 %
b11110101 *
b11110101 ,
b11110101 1
b11000101001011100101111111000101 )
b110011 '
#5130
1&
#5140
0&
#5150
1&
#5160
0&
#5170
1&
#5180
0&
#5190
1&
#5200
0&
#5210
1&
#5220
0&
b101010 %
b101010 *
b101010 ,
b101010 1
b10100000110001001011000111000010 )
b110100 '
#5230
12
0"
04
1&
#5240
0&
#5250
1#
13
02
1&
#5260
0&
#5270
b100 $
b100 +
b100 -
1.
0!
1&
#5280
0&
#5290
b110 $
b110 +
b110 -
1/
0.
1&
#5300
0&
#5310
1&
#5320
0&
b11001000 %
b11001000 *
b11001000 ,
b11001000 1
b1101100010010110011001001011011 )
b110101 '
#5330
1!
b0 $
b0 +
b0 -
0.
0/
12
0#
03
1&
#5340
0&
#5350
1"
14
02
1&
#5360
0&
#5370
1&
#5380
0&
#5390
1&
#5400
0&
#5410
1&
#5420
0&
b101 %
b101 *
b101 ,
b101 1
b10111100001000001111000111100000 )
b110110 '
#5430
1&
#5440
0&
#5450
1&
#5460
0&
#5470
1&
#5480
0&
#5490
1&
#5500
0&
#5510
1&
#5520
0&
b11011100 %
b11011100 *
b11011100 ,
b11011100 1
b1000100100010100001000001100001 )
b110111 '
#5530
1&
#5540
0&
#5550
1&
#5560
0&
#5570
1&
#5580
0&
#5590
1&
#5600
0&
#5610
1&
#5620
0&
b11111011 %
b11111011 *
b11111011 ,
b11111011 1
b11110101110001010000101010101110 )
b111000 '
#5630
1&
#5640
0&
#5650
1&
#5660
0&
#5670
1&
#5680
0&
#5690
1&
#5700
0&
#5710
1&
#5720
0&
b0 %
b0 *
b0 ,
b0 1
b11011011000000100110001101010111 )
b111001 '
#5730
1&
#5740
0&
#5750
1&
#5760
0&
#5770
1&
#5780
0&
#5790
1&
#5800
0&
#5810
1&
#5820
0&
b100010 %
b100010 *
b100010 ,
b100010 1
b11100011010010111111011110101100 )
b111010 '
#5830
12
0"
04
1&
#5840
0&
#5850
1&
#5860
0&
#5870
1&
#5880
0&
#5890
1&
#5900
0&
#5910
1&
#5920
0&
b110110 %
b110110 *
b110110 ,
b110110 1
b11010111000101010001000010111101 )
b111011 '
#5930
1#
13
02
1&
#5940
0&
#5950
b100 $
b100 +
b100 -
1.
0!
1&
#5960
0&
#5970
b110 $
b110 +
b110 -
1/
0.
1&
#5980
0&
#5990
b1000 $
b1000 +
b1000 -
10
0/
1&
#6000
0&
#6010
1&
#6020
0&
b10110000 %
b10110000 *
b10110000 ,
b10110000 1
b1011110011101010000000001011010 )
b111100 '
#6030
1!
b0 $
b0 +
b0 -
0/
00
12
0#
03
1&
#6040
0&
#6050
1"
14
02
1&
#6060
0&
#6070
1&
#6080
0&
#6090
1&
#6100
0&
#6110
1&
#6120
0&
b101 %
b101 *
b101 ,
b101 1
b10010101000011111101101000010011 )
b111101 '
#6130
1&
#6140
0&
#6150
1&
#6160
0&
#6170
1&
#6180
0&
#6190
1&
#6200
0&
#6210
1&
#6220
0&
b10110000 %
b10110000 *
b10110000 ,
b10110000 1
b101110101111001100000111000 )
b111110 '
#6230
1&
#6240
0&
#6250
1&
#6260
0&
#6270
1&
#6280
0&
#6290
1&
#6300
0&
#6310
1&
#6320
0&
b10111110 %
b10111110 *
b10111110 ,
b10111110 1
b111000100101111011110011011001 )
b111111 '
#6330
1&
#6340
0&
#6350
1&
#6360
0&
#6370
1&
#6380
0&
#6390
1&
#6400
0&
#6410
1&
#6420
0&
b1000000 '
